{
  "personalInfo": {
    "name": "samuido",
    "realName": "木村友亮",
    "title": "Web開発者・デザイナー",
    "location": "Japan",
    "avatar": "/images/avatar.jpg",
    "bio": "モダンな技術でユーザー体験を向上させることに情熱を注いでいるWeb開発者・デザイナーです。特にNext.js、TypeScript、TailwindCSSを使った高性能なWebサイト構築を得意としています。"
  },
  "contact": {
    "email": "rebuild.up.up@gmail.com",
    "website": "https://yusuke-kim.com",
    "github": "https://github.com/samuido",
    "twitter": "https://twitter.com/361do_sleep",
    "booth": "https://samuido.booth.pm/"
  },
  "skills": {
    "frontend": [
      { "name": "HTML/CSS", "level": 95 },
      { "name": "JavaScript", "level": 90 },
      { "name": "TypeScript", "level": 85 },
      { "name": "React", "level": 90 },
      { "name": "Next.js", "level": 85 },
      { "name": "TailwindCSS", "level": 90 },
      { "name": "Vue.js", "level": 75 }
    ],
    "backend": [
      { "name": "Node.js", "level": 80 },
      { "name": "Python", "level": 70 },
      { "name": "PHP", "level": 65 }
    ],
    "tools": [
      { "name": "Git", "level": 85 },
      { "name": "Docker", "level": 70 },
      { "name": "Figma", "level": 80 },
      { "name": "Photoshop", "level": 75 },
      { "name": "After Effects", "level": 80 }
    ],
    "languages": [
      { "name": "日本語", "level": 100 },
      { "name": "English", "level": 65 }
    ]
  },
  "experience": [
    {
      "company": "フリーランス",
      "position": "Web開発者・デザイナー",
      "period": "2020年 - 現在",
      "description": "個人事業主として、企業サイト制作、Webアプリケーション開発、UIデザイン、プラグイン開発などを手がける。モダンな技術スタックを使った高品質なWeb制作を提供。",
      "achievements": [
        "企業サイト制作 20件以上",
        "WordPressプラグイン開発・販売",
        "UIコンポーネントライブラリ開発",
        "業務効率化ツール開発"
      ]
    },
    {
      "company": "デザイン制作会社",
      "position": "Webデザイナー",
      "period": "2018年 - 2020年",
      "description": "企業のブランディングサイト、ECサイトのデザイン・コーディングを担当。ユーザビリティを重視したデザイン設計とレスポンシブ対応。",
      "achievements": [
        "大手企業サイトリニューアル",
        "コンバージョン率30%向上",
        "アクセシビリティ対応実装"
      ]
    }
  ],
  "education": [
    {
      "school": "専門学校",
      "degree": "デザイン学科",
      "period": "2016年 - 2018年",
      "description": "グラフィックデザイン、Webデザインの基礎を学習。卒業制作では企業サイトのリブランディング提案を実施。"
    }
  ]
}